lomography/__init__.py
lomography/api/cameras.py
lomography/api/films.py
lomography/api/location.py
lomography/api/photos.py
lomography/api/types.py
lomography/base.py
lomography/constants.py
lomography/objects/__init__.py
lomography/objects/camera.py
lomography/objects/film.py
lomography/objects/image.py
lomography/objects/lens.py
lomography/objects/photo.py
lomography/objects/tag.py
lomography/objects/user.py
lomography/utils/__init__.py
lomography/utils/misc.py
lomography/utils/requests.py
python_lomography-1.0.2.dist-info/LICENSE
python_lomography-1.0.2.dist-info/METADATA
python_lomography-1.0.2.dist-info/WHEEL
python_lomography-1.0.2.dist-info/RECORD
