Metadata-Version: 2.1
Name: python-lomography
Version: 1.0.2
Summary: A Python SDK for fetching images from the lomography.com API.
Author: Mike Scornavacca
Author-email: 52425912+scornz@users.noreply.github.com
Requires-Python: >=3.10,<4.0
Classifier: Programming Language :: Python :: 3
Classifier: Programming Language :: Python :: 3.10
Classifier: Programming Language :: Python :: 3.11
Classifier: Programming Language :: Python :: 3.12
Requires-Dist: aiohttp (>=3.9.5,<4.0.0)
